{"Bag  Text with Region Delimiter structure": "Iptc4xmpExt:DataOnScreen", "Bag Artwork/Object structure": "Iptc4xmpExt:ArtworkOrObject", "Bag CV Term structure": "Iptc4xmpExt:Genre", "Bag Embedded Encoded Rights Expression structure": "Iptc4xmpExt:EmbdEncRightsExpr", "Bag Enitity with Role structure": "Iptc4xmpExt:PlanningRef", "Bag Entity structure": "Iptc4xmpExt:EventExt", "Bag Entity with Role structure": "Iptc4xmpExt:Creator", "Bag Lang Alt": "dc:subject", "Bag Linked Encoded Rights Expression structure": "Iptc4xmpExt:LinkedEncRightsExpr", "Bag Linked Image": "Iptc4xmpExt:SnapshotLink", "Bag Location structure": "Iptc4xmpExt:LocationShown", "Bag PersonWDetails structure": "Iptc4xmpExt:PersonInImageWDetails", "Bag Product structure": "Iptc4xmpExt:ProductInImage", "Bag Publication Event structure": "Iptc4xmpExt:PublicationEvent", "Bag Qualified Link": "Iptc4xmpExt:TranscriptLink", "Bag Qualified Link with Language": "Iptc4xmpExt:TimedTextLink", "Bag Rating structure": "Iptc4xmpExt:ReviewRating", "Bag Registry Entry (structure)": "Iptc4xmpExt:RegistryId", "Bag Text\nBag Text": "Iptc4xmpExt:OrganisationInImageName\nIptc4xmpExt:OrganisationInImageCode", "Bag of CV Term structure": "Iptc4xmpExt:ContentWarning", "Bag of Text": "Iptc4xmpExt:StorylineIdentifier", "Bag of URL": "Iptc4xmpExt:ExternalMetadataLink", "Boolean": "Iptc4xmpExt:ReleaseReady", "CV Term structure": "Iptc4xmpExt:WorkflowTag", "Closed Choice\n- bw-monochrome\n- colour": "Iptc4xmpExt:VisualColour", "Closed Choice Real": "xmp:Rating", "Closed Choice Text": "xmpDM:audioChannelType", "Closed Choice Text\n- fixed\n- variable": "Iptc4xmpExt:audioBitRateMode", "Closed Choice or\nInteger": "Iptc4xmpExt:audioChannelCount", "Date": "Iptc4xmpExt:metadataLastEdited", "Device structure": "Iptc4xmpExt:RecDevice", "Entity structure": "Iptc4xmpExt:ContainerFormat", "Episode structure": "Iptc4xmpExt:Episode", "Integer": "Iptc4xmpExt:audioBitsPerSample", "Lang Alt": "dc:rights", "Marker": "xmpDM:markers[xmpDM:type= \"ivqu:editorialDurationStart\"] /xmpDM:startTime", "Rational": "xmpDM:fileDataRate", "Season structure": "Iptc4xmpExt:Season", "Series structure": "Iptc4xmpExt:Series", "Temporal Coverage Structure": "Iptc4xmpExt:TemporalCoverage", "Text": "xmpDM:audioCompressor", "Text Closed Choice": "dc:language", "Time": "xmpDM:duration", "number": "Iptc4xmpExt:CopyrightYear", "see PLUS spec": "plus:ImageSupplier"}